and_snake/__init__.py
and_snake/cpu_player.py
and_snake/game_client.py
and_snake/human_player.py
and_snake/play_snake.py
and_snake/snake_client.py
and_snake/utils.py
and_snake-1.3.0.dist-info/METADATA
and_snake-1.3.0.dist-info/WHEEL
and_snake-1.3.0.dist-info/entry_points.txt
and_snake-1.3.0.dist-info/RECORD
